messages_extends/__init__.py
messages_extends/admin.py
messages_extends/constants.py
messages_extends/exceptions.py
messages_extends/models.py
messages_extends/storages.py
messages_extends/urls.py
messages_extends/views.py
messages_extends/migrations/0001_initial.py
messages_extends/migrations/__init__.py
messages_extends/static/close-alerts.js
messages_extends/templates/messages_extends/includes/alerts_bootstrap.html
django_messages_extends-0.6.3.dist-info/LICENSE.txt
django_messages_extends-0.6.3.dist-info/METADATA
django_messages_extends-0.6.3.dist-info/WHEEL
django_messages_extends-0.6.3.dist-info/top_level.txt
django_messages_extends-0.6.3.dist-info/RECORD
