Metadata-Version: 2.1
Name: django-messages-extends
Version: 0.6.3
Summary: A Django app for extends Django's messages framework, adds sticky messages and persistent messages
Home-page: https://github.com/AliLozano/django-messages-extends/
Author: AliLozano
Author-email: alilozanoc@gmail.com
License: MIT
Keywords: messages,django,persistent,sticky
Classifier: Development Status :: 5 - Production/Stable
Classifier: Environment :: Web Environment
Classifier: Intended Audience :: Developers
Classifier: License :: OSI Approved :: MIT License
Classifier: Operating System :: OS Independent
Classifier: Programming Language :: Python
Classifier: Framework :: Django
Requires-Python: >=3
License-File: LICENSE.txt
